open_to_close_api/__init__.py
open_to_close_api/agents.py
open_to_close_api/base_client.py
open_to_close_api/client.py
open_to_close_api/contacts.py
open_to_close_api/exceptions.py
open_to_close_api/properties.py
open_to_close_api/property_contacts.py
open_to_close_api/property_documents.py
open_to_close_api/property_emails.py
open_to_close_api/property_notes.py
open_to_close_api/property_tasks.py
open_to_close_api/py.typed
open_to_close_api/tags.py
open_to_close_api/teams.py
open_to_close_api/users.py
open_to_close_api-1.1.0.dist-info/METADATA
open_to_close_api-1.1.0.dist-info/WHEEL
open_to_close_api-1.1.0.dist-info/top_level.txt
open_to_close_api-1.1.0.dist-info/RECORD
