Metadata-Version: 2.4
Name: open-to-close-api
Version: 1.1.0
Summary: Python wrapper for the Open To Close API
Author-email: John Perry <john@theperry.group>
License-Expression: MIT
Project-URL: Homepage, https://github.com/theperrygroup/open-to-close-api
Project-URL: Bug Reports, https://github.com/theperrygroup/open-to-close-api/issues
Project-URL: Source, https://github.com/theperrygroup/open-to-close-api
Keywords: api,wrapper,open-to-close,real-estate
Classifier: Development Status :: 4 - Beta
Classifier: Intended Audience :: Developers
Classifier: Operating System :: OS Independent
Classifier: Programming Language :: Python :: 3
Classifier: Programming Language :: Python :: 3.8
Classifier: Programming Language :: Python :: 3.9
Classifier: Programming Language :: Python :: 3.10
Classifier: Programming Language :: Python :: 3.11
Classifier: Programming Language :: Python :: 3.12
Classifier: Topic :: Software Development :: Libraries :: Python Modules
Classifier: Typing :: Typed
Requires-Python: >=3.8
Requires-Dist: requests>=2.25.0
Requires-Dist: python-dotenv>=0.19.0
Provides-Extra: dev
Requires-Dist: pytest>=7.0.0; extra == "dev"
Requires-Dist: pytest-cov>=4.0.0; extra == "dev"
Requires-Dist: pytest-mock>=3.10.0; extra == "dev"
Requires-Dist: responses>=0.23.0; extra == "dev"
Requires-Dist: black>=23.0.0; extra == "dev"
Requires-Dist: flake8>=6.0.0; extra == "dev"
Requires-Dist: mypy>=1.0.0; extra == "dev"
Requires-Dist: isort>=5.12.0; extra == "dev"
Requires-Dist: pylint>=2.17.0; extra == "dev"
Requires-Dist: types-requests>=2.25.0; extra == "dev"
Requires-Dist: mkdocs>=1.5.0; extra == "dev"
Requires-Dist: mkdocs-material>=9.4.0; extra == "dev"
Requires-Dist: mkdocs-include-markdown-plugin>=6.0.0; extra == "dev"
Requires-Dist: mkdocs-minify-plugin>=0.7.0; extra == "dev"
Requires-Dist: mike>=2.0.0; extra == "dev"
